usr/__init__.py
usr/bin/__init__.py
usr/bin/weather.py
termocast-0.1.dist-info/LICENSE
termocast-0.1.dist-info/METADATA
termocast-0.1.dist-info/WHEEL
termocast-0.1.dist-info/entry_points.txt
termocast-0.1.dist-info/top_level.txt
termocast-0.1.dist-info/RECORD
