Metadata-Version: 2.1
Name: termocast
Version: 0.1
Summary: A simple weather cli
Home-page: https://github.com/swadhinbiswas/TermoCast
Author: Swadhin Biswas
Author-email: swadhinbiswas.cse@gmail.com
License: MIT
Keywords: weather cli,weather forecast,weather,cli,command line interface,terminal,command line,forecast
Classifier: Development Status :: 3 - Alpha
Classifier: Intended Audience :: Developers
Classifier: License :: OSI Approved :: MIT License
Classifier: Programming Language :: Python :: 3.9
Classifier: Programming Language :: Python :: 3.10
Classifier: Topic :: Software Development :: Libraries :: Python Modules
Classifier: Operating System :: POSIX :: Linux
License-File: LICENSE
Requires-Dist: requests
Requires-Dist: geocoder
Requires-Dist: rich
Requires-Dist: typer
